sum_05220/__init__.py
SUM_FUNCTION-0.0.1.dist-info/LICENSE.txt
SUM_FUNCTION-0.0.1.dist-info/METADATA
SUM_FUNCTION-0.0.1.dist-info/WHEEL
SUM_FUNCTION-0.0.1.dist-info/top_level.txt
SUM_FUNCTION-0.0.1.dist-info/RECORD
